dockeb/__init__.py
dockeb/cli.py
dockeb-0.3.0.dist-info/LICENSE
dockeb-0.3.0.dist-info/METADATA
dockeb-0.3.0.dist-info/WHEEL
dockeb-0.3.0.dist-info/entry_points.txt
dockeb-0.3.0.dist-info/top_level.txt
dockeb-0.3.0.dist-info/RECORD
