Metadata-Version: 2.1
Name: dockeb
Version: 0.3.0
Summary: The Keb Docker wrapper
Home-page: https://github.com/abusque/dockeb
Author: Antoine Busque
Author-email: antoinebusque@gmail.com
License: MIT
Keywords: docker,wrapper,quebec
Platform: UNKNOWN
Classifier: License :: OSI Approved :: MIT License
Classifier: Programming Language :: Python
Classifier: Programming Language :: Python :: 3
Classifier: Programming Language :: Python :: 3.4
Classifier: Programming Language :: Python :: 3.5
Classifier: Programming Language :: Python :: 3.6
Classifier: Programming Language :: Python :: 3.7
Requires-Dist: qng (<2.0.0,>=1.0.0)
